odoo/addons/calendar_resource/README.rst
odoo/addons/calendar_resource/__init__.py
odoo/addons/calendar_resource/__manifest__.py
odoo/addons/calendar_resource/demo/resource_calendar.xml
odoo/addons/calendar_resource/demo/resource_calendar_attendance.xml
odoo/addons/calendar_resource/i18n/ar.po
odoo/addons/calendar_resource/i18n/bg.po
odoo/addons/calendar_resource/i18n/bs.po
odoo/addons/calendar_resource/i18n/ca.po
odoo/addons/calendar_resource/i18n/calendar_resource.pot
odoo/addons/calendar_resource/i18n/cs.po
odoo/addons/calendar_resource/i18n/da.po
odoo/addons/calendar_resource/i18n/de.po
odoo/addons/calendar_resource/i18n/en_GB.po
odoo/addons/calendar_resource/i18n/es.po
odoo/addons/calendar_resource/i18n/es_AR.po
odoo/addons/calendar_resource/i18n/es_CL.po
odoo/addons/calendar_resource/i18n/es_CO.po
odoo/addons/calendar_resource/i18n/es_CR.po
odoo/addons/calendar_resource/i18n/es_DO.po
odoo/addons/calendar_resource/i18n/es_EC.po
odoo/addons/calendar_resource/i18n/es_MX.po
odoo/addons/calendar_resource/i18n/es_PE.po
odoo/addons/calendar_resource/i18n/es_PY.po
odoo/addons/calendar_resource/i18n/es_VE.po
odoo/addons/calendar_resource/i18n/et.po
odoo/addons/calendar_resource/i18n/eu.po
odoo/addons/calendar_resource/i18n/fa.po
odoo/addons/calendar_resource/i18n/fi.po
odoo/addons/calendar_resource/i18n/fr.po
odoo/addons/calendar_resource/i18n/fr_CA.po
odoo/addons/calendar_resource/i18n/he.po
odoo/addons/calendar_resource/i18n/hr.po
odoo/addons/calendar_resource/i18n/hu.po
odoo/addons/calendar_resource/i18n/id.po
odoo/addons/calendar_resource/i18n/it.po
odoo/addons/calendar_resource/i18n/ja.po
odoo/addons/calendar_resource/i18n/ko.po
odoo/addons/calendar_resource/i18n/lt.po
odoo/addons/calendar_resource/i18n/lv.po
odoo/addons/calendar_resource/i18n/mk.po
odoo/addons/calendar_resource/i18n/mn.po
odoo/addons/calendar_resource/i18n/nb.po
odoo/addons/calendar_resource/i18n/nl.po
odoo/addons/calendar_resource/i18n/nl_BE.po
odoo/addons/calendar_resource/i18n/nl_NL.po
odoo11_addon_calendar_resource-11.0.1.0.0.99.dev34.dist-info/METADATA
odoo11_addon_calendar_resource-11.0.1.0.0.99.dev34.dist-info/WHEEL
odoo11_addon_calendar_resource-11.0.1.0.0.99.dev34.dist-info/top_level.txt
odoo11_addon_calendar_resource-11.0.1.0.0.99.dev34.dist-info/RECORD
